sixel/__about__.py
sixel/__init__.py
sixel/cellsize.py
sixel/converter.py
sixel/sixel.py
sixel-0.2.0.dist-info/METADATA
sixel-0.2.0.dist-info/WHEEL
sixel-0.2.0.dist-info/entry_points.txt
sixel-0.2.0.dist-info/licenses/LICENSE
sixel-0.2.0.dist-info/RECORD
