Metadata-Version: 2.1
Name: sixel
Version: 0.2.0
Summary: Display images in the terminal
Project-URL: Homepage, https://github.com/lubosz/python-sixel
Project-URL: Bug Tracker, https://github.com/lubosz/python-sixel/issues
Author-email: Hayaki Saito <user@zuse.jp>, Lubosz Sarnecki <lubosz@gmail.com>
Maintainer-email: Lubosz Sarnecki <lubosz@gmail.com>
License-Expression: GPL-3.0-or-later
License-File: LICENSE
Keywords: image,sixel,terminal
Classifier: Development Status :: 4 - Beta
Classifier: Environment :: Console
Classifier: Intended Audience :: End Users/Desktop
Classifier: License :: OSI Approved :: GNU General Public License (GPL)
Classifier: Operating System :: OS Independent
Classifier: Programming Language :: Python :: 3
Classifier: Topic :: Terminals
Requires-Python: >=3.0
Requires-Dist: pillow
